.class public Main
.super java/lang/Object


.method public static main ([Ljava/lang/String;)V

getstatic java/lang/System/out Ljava/io/PrintStream;
ldc_w 65535
i2c
invokevirtual java/io/PrintStream/print(I)V
getstatic java/lang/System/out Ljava/io/PrintStream;
ldc_w "
"
invokevirtual java/io/PrintStream/print(Ljava/lang/String;)V

getstatic java/lang/System/out Ljava/io/PrintStream;
ldc_w 32767
i2s
invokevirtual java/io/PrintStream/print(I)V
getstatic java/lang/System/out Ljava/io/PrintStream;
ldc_w "
"
invokevirtual java/io/PrintStream/print(Ljava/lang/String;)V

getstatic java/lang/System/out Ljava/io/PrintStream;
ldc_w 2147483647
i2l
invokevirtual java/io/PrintStream/print(J)V
getstatic java/lang/System/out Ljava/io/PrintStream;
ldc_w "
"
invokevirtual java/io/PrintStream/print(Ljava/lang/String;)V

getstatic java/lang/System/out Ljava/io/PrintStream;
ldc2_w 2147483647
l2i
invokevirtual java/io/PrintStream/print(I)V
getstatic java/lang/System/out Ljava/io/PrintStream;
ldc_w "
"
invokevirtual java/io/PrintStream/print(Ljava/lang/String;)V

getstatic java/lang/System/out Ljava/io/PrintStream;
ldc_w 65538
i2c
invokevirtual java/io/PrintStream/print(I)V
getstatic java/lang/System/out Ljava/io/PrintStream;
ldc_w "
"
invokevirtual java/io/PrintStream/print(Ljava/lang/String;)V

getstatic java/lang/System/out Ljava/io/PrintStream;
ldc_w 32770
i2s
invokevirtual java/io/PrintStream/print(I)V
getstatic java/lang/System/out Ljava/io/PrintStream;
ldc_w "
"
invokevirtual java/io/PrintStream/print(Ljava/lang/String;)V

getstatic java/lang/System/out Ljava/io/PrintStream;
ldc_w -2147483648
i2l
invokevirtual java/io/PrintStream/print(J)V
getstatic java/lang/System/out Ljava/io/PrintStream;
ldc_w "
"
invokevirtual java/io/PrintStream/print(Ljava/lang/String;)V

getstatic java/lang/System/out Ljava/io/PrintStream;
ldc2_w 2147483650
l2i
invokevirtual java/io/PrintStream/print(I)V
getstatic java/lang/System/out Ljava/io/PrintStream;
ldc_w "
"
invokevirtual java/io/PrintStream/print(Ljava/lang/String;)V

return

.end method


.end class
